structured_prompts/__init__.py
structured_prompts/database.py
structured_prompts/input_validation.py
structured_prompts/model_capabilities.py
structured_prompts/models.py
structured_prompts/schema_manager.py
structured_prompts/interfaces/__init__.py
structured_prompts/interfaces/mcp.py
structured_prompts-0.1.1.dist-info/METADATA
structured_prompts-0.1.1.dist-info/WHEEL
structured_prompts-0.1.1.dist-info/entry_points.txt
structured_prompts-0.1.1.dist-info/top_level.txt
structured_prompts-0.1.1.dist-info/RECORD
