Metadata-Version: 2.4
Name: structured-prompts
Version: 0.1.1
Summary: A modular package for managing structured prompts with any LLM API
Home-page: https://github.com/ebowwa/structured-prompts
Author: ebowwa
Author-email: your.email@example.com
Classifier: Development Status :: 3 - Alpha
Classifier: Intended Audience :: Developers
Classifier: Topic :: Software Development :: Libraries :: Python Modules
Classifier: License :: OSI Approved :: MIT License
Classifier: Programming Language :: Python :: 3
Classifier: Programming Language :: Python :: 3.9
Classifier: Programming Language :: Python :: 3.10
Classifier: Programming Language :: Python :: 3.11
Requires-Python: >=3.9
Requires-Dist: fastapi>=0.104.0
Requires-Dist: sqlalchemy<1.5,>=1.4.42
Requires-Dist: sqlalchemy-utils>=0.41.0
Requires-Dist: pydantic>=2.5.0
Requires-Dist: databases>=0.8.0
Requires-Dist: asyncpg>=0.29.0
Requires-Dist: mcp>=1.0.0
Dynamic: author
Dynamic: author-email
Dynamic: classifier
Dynamic: description
Dynamic: description-content-type
Dynamic: home-page
Dynamic: requires-dist
Dynamic: requires-python
Dynamic: summary
